idhash-0.3.0.dist-info/METADATA
idhash-0.3.0.dist-info/WHEEL
idhash/__pycache__/__init__.cpython-38.pyc
idhash/__init__.py
idhash/py.typed
idhash/idhash.cpython-310-x86_64-linux-gnu.so
idhash-0.3.0.dist-info/RECORD
