Metadata-Version: 2.1
Name: idhash
Version: 0.3.0
Classifier: Development Status :: 4 - Beta
Requires-Dist: pandas
Requires-Dist: pyarrow
Requires-Dist: numpy
Summary: Calculate the Unique Numeric Fingerprint for Tabular Data
Keywords: data,hash
Author: Lissa Hyacinth <lissahyacinth@gmail.com>
Author-email: Lissa Hyacinth <lissahyacinth@gmail.com>
License: GPL-2.0-or-later
Project-URL: Source Code, https://github.com/lissahyacinth/idhash-py
